sndls/__init__.py
sndls/cli/__init__.py
sndls/cli/cmd.py
sndls/cli/main.py
sndls/utils/__init__.py
sndls/utils/audio.py
sndls/utils/collections.py
sndls/utils/config.py
sndls/utils/exceptions.py
sndls/utils/fmt.py
sndls/utils/guards.py
sndls/utils/hash.py
sndls/utils/io.py
sndls-0.1.10.dist-info/entry_points.txt
sndls-0.1.10.dist-info/LICENSE
sndls-0.1.10.dist-info/WHEEL
sndls-0.1.10.dist-info/METADATA
sndls-0.1.10.dist-info/RECORD
